stringutils/__init__.py
stringutils/utils.py
pytholic_stringutils-0.1.3.dist-info/METADATA
pytholic_stringutils-0.1.3.dist-info/WHEEL
pytholic_stringutils-0.1.3.dist-info/top_level.txt
pytholic_stringutils-0.1.3.dist-info/RECORD
