Metadata-Version: 2.1
Name: pytholic-stringutils
Version: 0.1.3
Requires-Python: >=3.8
Requires-Dist: numpy
Requires-Dist: twine
